ilabs.matchback-0.1.3-py3.8-nspkg.pth
ilabs/matchback/__init__.py
ilabs/matchback/main.py
ilabs.matchback-0.1.3.dist-info/LICENSE
ilabs.matchback-0.1.3.dist-info/METADATA
ilabs.matchback-0.1.3.dist-info/WHEEL
ilabs.matchback-0.1.3.dist-info/entry_points.txt
ilabs.matchback-0.1.3.dist-info/namespace_packages.txt
ilabs.matchback-0.1.3.dist-info/top_level.txt
ilabs.matchback-0.1.3.dist-info/RECORD
