Metadata-Version: 2.1
Name: ilabs.matchback
Version: 0.1.3
Summary: A tool to match inno:dom content back to the source HTML
Home-page: https://github.com/innodatalabs/ilabs.matchback
Author: Mike Kroutikov
Author-email: mkroutikov@innodata.com
License: MIT
Keywords: innodata inno:dom xml html
Platform: UNKNOWN
Classifier: Development Status :: 4 - Beta
Classifier: Intended Audience :: Developers
Classifier: License :: OSI Approved :: MIT License
Classifier: Programming Language :: Python :: 3
Classifier: Programming Language :: Python :: 3.6
Classifier: Programming Language :: Python :: 3.7
Classifier: Programming Language :: Python :: 3.8
Requires-Dist: lxml
